{
  "abstract": false,
  "anchor": "",
  "baseClasses": [
    {
      "external": true,
      "name": "std::true_type",
      "refid": null,
      "virtual": "non-virtual",
      "visibility": "public"
    }
  ],
  "category": "classes",
  "const": false,
  "definition": "",
  "explicit": false,
  "fullname": "thrust::detail::conjunction",
  "hasAdditionalMembers": false,
  "hasDetails": true,
  "inline": false,
  "kind": "struct",
  "language": "cpp",
  "location": {
    "bodyEnd": 198,
    "bodyFile": "thrust/optional.h",
    "bodyStart": 198,
    "column": 11,
    "file": "thrust/optional.h",
    "line": 198
  },
  "name": "thrust::detail::conjunction",
  "override": false,
  "parent": {
    "anchor": "",
    "brief": "\\exclude ",
    "category": "namespaces",
    "fullname": "thrust::detail",
    "kind": "namespace",
    "language": "cpp",
    "name": "thrust::detail",
    "qualifiedname": "thrust::detail",
    "refid": "namespacethrust_1_1detail",
    "summary": "\\exclude ",
    "title": "thrust::detail",
    "url": "{{ site.baseurl }}/api/namespaces/namespacethrust_1_1detail.html",
    "visibility": "public"
  },
  "parentBreadcrumbs": [
    {
      "anchor": "",
      "category": "namespaces",
      "fullname": "thrust",
      "kind": "namespace",
      "language": "cpp",
      "name": "thrust",
      "qualifiedname": "thrust",
      "refid": "namespacethrust",
      "title": "thrust",
      "url": "{{ site.baseurl }}/api/namespaces/namespacethrust.html",
      "visibility": "public"
    },
    {
      "anchor": "",
      "brief": "\\exclude ",
      "category": "namespaces",
      "fullname": "thrust::detail",
      "kind": "namespace",
      "language": "cpp",
      "name": "thrust::detail",
      "qualifiedname": "thrust::detail",
      "refid": "namespacethrust_1_1detail",
      "summary": "\\exclude ",
      "title": "thrust::detail",
      "url": "{{ site.baseurl }}/api/namespaces/namespacethrust_1_1detail.html",
      "visibility": "public"
    }
  ],
  "qualifiedname": "thrust::detail::conjunction",
  "refid": "structthrust_1_1detail_1_1conjunction",
  "static": false,
  "strong": false,
  "templateParams": [
    {
      "name": "",
      "type": "class...",
      "typePlain": "class..."
    }
  ],
  "title": "thrust::detail::conjunction",
  "url": "{{ site.baseurl }}/api/classes/structthrust_1_1detail_1_1conjunction.html",
  "visibility": "public"
}